<annotation verified="yes">
    <folder>Annotation</folder>
    <filename>file57.jpg</filename>
    <path>item-PascalVOC-export/Annotations/file57.jpg</path>
    <source>
        <database>Unknown</database>
    </source>
    <size>
        <width>64</width>
        <height>64</height>
        <depth>3</depth>
    </size>
    <segmented>0</segmented>
    <object>
    <name>human</name>
    <pose>Unspecified</pose>
    <truncated>0</truncated>
    <difficult>0</difficult>
    <bndbox>
        <xmin>16.74094401756312</xmin>
        <ymin>9.927826564215149</ymin>
        <xmax>29.54829857299671</xmax>
        <ymax>30.15312843029638</ymax>
    </bndbox>
</object>
</annotation>
